<PAMDataset>
  <Metadata domain="IMAGE_STRUCTURE">
    <MDI key="INTERLEAVE">PIXEL</MDI>
  </Metadata>
  <PAMRasterBand band="1">
    <Metadata>
      <MDI key="STATISTICS_APPROXIMATE">YES</MDI>
      <MDI key="STATISTICS_MINIMUM">1</MDI>
      <MDI key="STATISTICS_MAXIMUM">175</MDI>
      <MDI key="STATISTICS_MEAN">49.661137045682</MDI>
      <MDI key="STATISTICS_STDDEV">34.049732083026</MDI>
      <MDI key="STATISTICS_VALID_PERCENT">36.61</MDI>
    </Metadata>
  </PAMRasterBand>
  <PAMRasterBand band="2">
    <Metadata>
      <MDI key="STATISTICS_APPROXIMATE">YES</MDI>
      <MDI key="STATISTICS_MINIMUM">1</MDI>
      <MDI key="STATISTICS_MAXIMUM">175</MDI>
      <MDI key="STATISTICS_MEAN">49.660470156719</MDI>
      <MDI key="STATISTICS_STDDEV">34.049088897217</MDI>
      <MDI key="STATISTICS_VALID_PERCENT">36.61</MDI>
    </Metadata>
  </PAMRasterBand>
  <PAMRasterBand band="3">
    <Metadata>
      <MDI key="STATISTICS_APPROXIMATE">YES</MDI>
      <MDI key="STATISTICS_MINIMUM">1</MDI>
      <MDI key="STATISTICS_MAXIMUM">175</MDI>
      <MDI key="STATISTICS_MEAN">49.660386795599</MDI>
      <MDI key="STATISTICS_STDDEV">34.047206523803</MDI>
      <MDI key="STATISTICS_VALID_PERCENT">36.61</MDI>
    </Metadata>
  </PAMRasterBand>
</PAMDataset>
