<PAMDataset>
  <Metadata domain="IMAGE_STRUCTURE">
    <MDI key="INTERLEAVE">PIXEL</MDI>
  </Metadata>
  <PAMRasterBand band="1">
    <Metadata>
      <MDI key="STATISTICS_APPROXIMATE">YES</MDI>
      <MDI key="STATISTICS_MINIMUM">25</MDI>
      <MDI key="STATISTICS_MAXIMUM">230</MDI>
      <MDI key="STATISTICS_MEAN">109.06555175781</MDI>
      <MDI key="STATISTICS_STDDEV">20.517107413556</MDI>
      <MDI key="STATISTICS_VALID_PERCENT">100</MDI>
    </Metadata>
  </PAMRasterBand>
  <PAMRasterBand band="2">
    <Metadata>
      <MDI key="STATISTICS_APPROXIMATE">YES</MDI>
      <MDI key="STATISTICS_MINIMUM">25</MDI>
      <MDI key="STATISTICS_MAXIMUM">230</MDI>
      <MDI key="STATISTICS_MEAN">109.0647277832</MDI>
      <MDI key="STATISTICS_STDDEV">20.517765228035</MDI>
      <MDI key="STATISTICS_VALID_PERCENT">100</MDI>
    </Metadata>
  </PAMRasterBand>
  <PAMRasterBand band="3">
    <Metadata>
      <MDI key="STATISTICS_APPROXIMATE">YES</MDI>
      <MDI key="STATISTICS_MINIMUM">25</MDI>
      <MDI key="STATISTICS_MAXIMUM">230</MDI>
      <MDI key="STATISTICS_MEAN">109.06588745117</MDI>
      <MDI key="STATISTICS_STDDEV">20.516705474357</MDI>
      <MDI key="STATISTICS_VALID_PERCENT">100</MDI>
    </Metadata>
  </PAMRasterBand>
</PAMDataset>
